FiveSimApi/__init__.py
FiveSimApi/fivesim.py
fivesimapi-0.2.dist-info/LICENSE
fivesimapi-0.2.dist-info/METADATA
fivesimapi-0.2.dist-info/WHEEL
fivesimapi-0.2.dist-info/top_level.txt
fivesimapi-0.2.dist-info/RECORD
