Metadata-Version: 2.1
Name: fivesimapi
Version: 0.2
Summary: A python Api wrapper of 5sim.net
Home-page: https://github.com/Subrata2402/fivesimapi
Author: Subrata
Author-email: 
Classifier: Programming Language :: Python :: 3.8
Classifier: License :: OSI Approved :: GNU General Public License v3 (GPLv3)
Classifier: Operating System :: OS Independent
Requires-Python: >=3.8
License-File: LICENSE
Requires-Dist: aiohttp
